betterspy/__about__.py
betterspy/__init__.py
betterspy/cli.py
betterspy/main.py
betterspy-0.1.6.dist-info/LICENSE.txt
betterspy-0.1.6.dist-info/METADATA
betterspy-0.1.6.dist-info/WHEEL
betterspy-0.1.6.dist-info/entry_points.txt
betterspy-0.1.6.dist-info/top_level.txt
betterspy-0.1.6.dist-info/RECORD
