Metadata-Version: 2.1
Name: betterspy
Version: 0.1.6
Summary: Show sparsity patterns of sparse matrices
Home-page: https://github.com/nschloe/betterspy
Author: Nico Schlömer
License: GPL-3.0-or-later
Project-URL: Code, https://github.com/nschloe/betterspy
Project-URL: Issues, https://github.com/nschloe/betterspy/issues
Project-URL: Funding, https://github.com/sponsors/nschloe
Platform: UNKNOWN
Classifier: Development Status :: 4 - Beta
Classifier: Intended Audience :: Science/Research
Classifier: License :: OSI Approved :: GNU General Public License v3 or later (GPLv3+)
Classifier: Operating System :: OS Independent
Classifier: Programming Language :: Python
Classifier: Programming Language :: Python :: 3
Classifier: Programming Language :: Python :: 3.6
Classifier: Programming Language :: Python :: 3.7
Classifier: Programming Language :: Python :: 3.8
Classifier: Programming Language :: Python :: 3.9
Classifier: Topic :: Scientific/Engineering
Classifier: Topic :: Utilities
Requires-Python: >=3.6
